math_mcp/__init__.py
math_mcp/server.py
scicomp_math_mcp-0.1.6.dist-info/METADATA
scicomp_math_mcp-0.1.6.dist-info/WHEEL
scicomp_math_mcp-0.1.6.dist-info/entry_points.txt
scicomp_math_mcp-0.1.6.dist-info/RECORD
