Metadata-Version: 2.4
Name: scicomp-math-mcp
Version: 0.1.6
Summary: MCP server for symbolic algebra and GPU-accelerated numerical computing
Project-URL: Homepage, https://github.com/andylbrummer/math-mcp
Project-URL: Documentation, https://andylbrummer.github.io/math-mcp/api/math-mcp
Project-URL: Repository, https://github.com/andylbrummer/math-mcp
Author-email: Andy Brummer <andy@example.com>
License-Expression: MIT
Keywords: algebra,gpu,math,mcp,model-context-protocol,symbolic,sympy
Classifier: Development Status :: 4 - Beta
Classifier: Intended Audience :: Developers
Classifier: Intended Audience :: Science/Research
Classifier: License :: OSI Approved :: MIT License
Classifier: Programming Language :: Python :: 3
Classifier: Programming Language :: Python :: 3.11
Classifier: Programming Language :: Python :: 3.12
Classifier: Topic :: Scientific/Engineering :: Mathematics
Requires-Python: >=3.11
Requires-Dist: mcp>=1.0.0
Requires-Dist: mpmath>=1.3.0
Requires-Dist: numpy>=1.26.0
Requires-Dist: scicomp-compute-core>=0.1.6
Requires-Dist: scicomp-mcp-common>=0.1.6
Requires-Dist: scipy>=1.11.0
Requires-Dist: sympy>=1.12
Provides-Extra: gpu
Requires-Dist: cupy-cuda12x>=13.0.0; extra == 'gpu'
